morse_tunes/__init__.py
morse_tunes/audio.py
morse_tunes/morse.py
morse_tunes-0.1.0.dist-info/METADATA
morse_tunes-0.1.0.dist-info/WHEEL
morse_tunes-0.1.0.dist-info/entry_points.txt
morse_tunes-0.1.0.dist-info/top_level.txt
morse_tunes-0.1.0.dist-info/RECORD
