Metadata-Version: 2.1
Name: morse-tunes
Version: 0.1.0
Summary: A library to convert text to Morse code and play it as audio.
Home-page: https://github.com/wisalkhanmv/morse-tunes
Author: Muhammad Wisal
Author-email: muhammadwisalkhanmv@example.com
Classifier: Programming Language :: Python :: 3
Classifier: License :: OSI Approved :: Apache Software License
Classifier: Operating System :: OS Independent
Requires-Python: >=3.7
